
{
	"仓库名":"ware",
	"方块位置":[
		{
			"方块":"白色土",
			"位置":1
		},
		{
			"方块":"品红土",
			"位置":2
		},
		{
			"方块":"粉红土",
			"位置":3
		},
		{
			"方块":"红色土",
			"位置":4
		},
		{
			"方块":"橙色土",
			"位置":5
		},
		{
			"方块":"黄色土",
			"位置":6
		},
		{
			"方块":"黄绿土",
			"位置":7
		},
		{
			"方块":"绿色土",
			"位置":8
		},
		{
			"方块":"绿色土",
			"位置":8
		},
		{
			"方块":"绿色土",
			"位置":8
		},
		{
			"方块":"青色土",
			"位置":9
		},
		{
			"方块":"淡蓝土",
			"位置":10
		},
		{
			"方块":"蓝色土",
			"位置":11
		},
		{
			"方块":"紫色土",
			"位置":12
		},
		{
			"方块":"棕色土",
			"位置":13
		},
		{
			"方块":"淡灰土",
			"位置":14
		},
		{
			"方块":"灰色土",
			"位置":15
		},
		{
			"方块":"黑色土",
			"位置":16
		},
		{
			"方块":"白色瓦",
			"位置":17
		},
		{
			"方块":"品红瓦",
			"位置":18
		},
		{
			"方块":"粉红瓦",
			"位置":19
		},
		{
			"方块":"红色瓦",
			"位置":20
		},
		{
			"方块":"橙色瓦",
			"位置":21
		},
		{
			"方块":"黄色瓦",
			"位置":22
		},
		{
			"方块":"黄绿瓦",
			"位置":23
		},
		{
			"方块":"绿色瓦",
			"位置":24
		},
		{
			"方块":"青色瓦",
			"位置":25
		},
		{
			"方块":"淡蓝瓦",
			"位置":26
		},
		{
			"方块":"蓝色瓦",
			"位置":27
		},
		{
			"方块":"紫色瓦",
			"位置":28
		},
		{
			"方块":"棕色瓦",
			"位置":29
		},
		{
			"方块":"淡灰瓦",
			"位置":30
		},
		{
			"方块":"灰色瓦",
			"位置":31
		},
		{
			"方块":"黑色瓦",
			"位置":32
		},
		{
			"方块":"海晶块",
			"位置":33
		},
		{
			"方块":"石英块",
			"位置":34
		},
		{
			"方块":"草方块",
			"位置":35
		},
		{
			"方块":"石头块",
			"位置":36
		},
		{
			"方块":"砂岩块",
			"位置":37
		},
		{
			"方块":"地狱岩",
			"位置":38
		},
		{
			"方块":"黏土块",
			"位置":39
		},
		{
			"方块":"浮冰块",
			"位置":40
		},
		{
			"方块":"花岗岩",
			"位置":41
		},
		{
			"方块":"灰土块",
			"位置":42
		},
		{
			"方块":"橡木板",
			"位置":43
		},
		{
			"方块":"炸弹块",
			"位置":44
		},
	]

}

